fwttools/__init__.py
fwttools/fwt_tools.py
fwttools/utils/__init__.py
fwttools/utils/analytiсal_gaussian.py
fwttools/utils/basis_wavelets.py
fwttools/utils/daubechies_coefficients.py
fwttools/utils/error.py
fwttools/utils/io.py
fwt_tools-1.0.7.dist-info/LICENSE
fwt_tools-1.0.7.dist-info/METADATA
fwt_tools-1.0.7.dist-info/WHEEL
fwt_tools-1.0.7.dist-info/top_level.txt
fwt_tools-1.0.7.dist-info/RECORD
