Metadata-Version: 2.1
Name: fwt-tools
Version: 1.0.7
Summary: Tools for building your own wavelets and performing fast wavelet transform
Home-page: https://github.com/spyr000/FwtTools
Author: spyr000
Author-email: mr.zeddd123@gmail.com
Project-URL: Documentation, https://github.com/spyr000/UsagesOfFwtTools
Keywords: example python
Classifier: Programming Language :: Python :: 3.11
Classifier: License :: OSI Approved :: MIT License
Classifier: Operating System :: OS Independent
Requires-Python: >=3.7
License-File: LICENSE
Requires-Dist: numpy >=1.20
Requires-Dist: numba >=0.60.0
